py_eth_utils/__init__.py
py_eth_utils/contract_api.py
py_eth_utils/eth_api.py
py_eth_utils/wallet_tools.py
py_eth_utils-0.0.5.dist-info/METADATA
py_eth_utils-0.0.5.dist-info/WHEEL
py_eth_utils-0.0.5.dist-info/top_level.txt
py_eth_utils-0.0.5.dist-info/RECORD
