Metadata-Version: 2.1
Name: py-eth-utils
Version: 0.0.5
Summary: eth for tools, contracts、transfer、balance
Author: Stars Bing
Author-email: bing@starsxu.com
Classifier: Programming Language :: Python :: 3.9
Classifier: License :: OSI Approved :: MIT License
Requires-Dist: web3 ==6.15.1
